{
  "players": {
    "white": "gertvv",
    "black": "tonyd33"
  },
  "type": "WIN",
  "winner": "tonyd33",
  "reason": "CHECKMATE",
  "pgn": "[Event \"?\"]\n[Site \"?\"]\n[Date \"????.??.??\"]\n[Round \"?\"]\n[White \"Silver Suite\"]\n[Black \"Alekhine, 4. Nf3\"]\n[Result \"*\"]\n[ECO \"B05\"]\n[PlyCount \"7\"]\n\n1. e4 Nf6 2. e5 Nd5 3. d4 d6 4. Nf3 Bg4 5. Be2 e6 6. Bf1 dxe5 7. Nbd2 exd4 8. Qe2 Nc6 9. Qc4 Qd7 10. Ne4 O-O-O 11. Nc3 Bxf3 12. Bg5 dxc3 13. Qb3 Ne3 14. Qb6 Nxc2# *",
  "moves": [
    {
      "color": "b",
      "from": "c8",
      "to": "g4",
      "piece": "b",
      "flags": "n",
      "san": "Bg4",
      "lan": "c8g4",
      "before": "rnbqkb1r/ppp1pppp/3p4/3nP3/3P4/5N2/PPP2PPP/RNBQKB1R b KQkq - 1 4",
      "after": "rn1qkb1r/ppp1pppp/3p4/3nP3/3P2b1/5N2/PPP2PPP/RNBQKB1R w KQkq - 2 5",
      "durationMs": 44.71770899929106
    },
    {
      "color": "w",
      "from": "f1",
      "to": "e2",
      "piece": "b",
      "flags": "n",
      "san": "Be2",
      "lan": "f1e2",
      "before": "rn1qkb1r/ppp1pppp/3p4/3nP3/3P2b1/5N2/PPP2PPP/RNBQKB1R w KQkq - 2 5",
      "after": "rn1qkb1r/ppp1pppp/3p4/3nP3/3P2b1/5N2/PPP1BPPP/RNBQK2R b KQkq - 3 5",
      "durationMs": 22.092917000874877
    },
    {
      "color": "b",
      "from": "e7",
      "to": "e6",
      "piece": "p",
      "flags": "n",
      "san": "e6",
      "lan": "e7e6",
      "before": "rn1qkb1r/ppp1pppp/3p4/3nP3/3P2b1/5N2/PPP1BPPP/RNBQK2R b KQkq - 3 5",
      "after": "rn1qkb1r/ppp2ppp/3pp3/3nP3/3P2b1/5N2/PPP1BPPP/RNBQK2R w KQkq - 0 6",
      "durationMs": 14.018332999199629
    },
    {
      "color": "w",
      "from": "e2",
      "to": "f1",
      "piece": "b",
      "flags": "n",
      "san": "Bf1",
      "lan": "e2f1",
      "before": "rn1qkb1r/ppp2ppp/3pp3/3nP3/3P2b1/5N2/PPP1BPPP/RNBQK2R w KQkq - 0 6",
      "after": "rn1qkb1r/ppp2ppp/3pp3/3nP3/3P2b1/5N2/PPP2PPP/RNBQKB1R b KQkq - 1 6",
      "durationMs": 4904.277083000168
    },
    {
      "color": "b",
      "from": "d6",
      "to": "e5",
      "piece": "p",
      "captured": "p",
      "flags": "c",
      "san": "dxe5",
      "lan": "d6e5",
      "before": "rn1qkb1r/ppp2ppp/3pp3/3nP3/3P2b1/5N2/PPP2PPP/RNBQKB1R b KQkq - 1 6",
      "after": "rn1qkb1r/ppp2ppp/4p3/3np3/3P2b1/5N2/PPP2PPP/RNBQKB1R w KQkq - 0 7",
      "durationMs": 4908.37808299996
    },
    {
      "color": "w",
      "from": "b1",
      "to": "d2",
      "piece": "n",
      "flags": "n",
      "san": "Nbd2",
      "lan": "b1d2",
      "before": "rn1qkb1r/ppp2ppp/4p3/3np3/3P2b1/5N2/PPP2PPP/RNBQKB1R w KQkq - 0 7",
      "after": "rn1qkb1r/ppp2ppp/4p3/3np3/3P2b1/5N2/PPPN1PPP/R1BQKB1R b KQkq - 1 7",
      "durationMs": 4742.80904199928
    },
    {
      "color": "b",
      "from": "e5",
      "to": "d4",
      "piece": "p",
      "captured": "p",
      "flags": "c",
      "san": "exd4",
      "lan": "e5d4",
      "before": "rn1qkb1r/ppp2ppp/4p3/3np3/3P2b1/5N2/PPPN1PPP/R1BQKB1R b KQkq - 1 7",
      "after": "rn1qkb1r/ppp2ppp/4p3/3n4/3p2b1/5N2/PPPN1PPP/R1BQKB1R w KQkq - 0 8",
      "durationMs": 4906.397957999259
    },
    {
      "color": "w",
      "from": "d1",
      "to": "e2",
      "piece": "q",
      "flags": "n",
      "san": "Qe2",
      "lan": "d1e2",
      "before": "rn1qkb1r/ppp2ppp/4p3/3n4/3p2b1/5N2/PPPN1PPP/R1BQKB1R w KQkq - 0 8",
      "after": "rn1qkb1r/ppp2ppp/4p3/3n4/3p2b1/5N2/PPPNQPPP/R1B1KB1R b KQkq - 1 8",
      "durationMs": 4901.534540999681
    },
    {
      "color": "b",
      "from": "b8",
      "to": "c6",
      "piece": "n",
      "flags": "n",
      "san": "Nc6",
      "lan": "b8c6",
      "before": "rn1qkb1r/ppp2ppp/4p3/3n4/3p2b1/5N2/PPPNQPPP/R1B1KB1R b KQkq - 1 8",
      "after": "r2qkb1r/ppp2ppp/2n1p3/3n4/3p2b1/5N2/PPPNQPPP/R1B1KB1R w KQkq - 2 9",
      "durationMs": 4909.583582999185
    },
    {
      "color": "w",
      "from": "e2",
      "to": "c4",
      "piece": "q",
      "flags": "n",
      "san": "Qc4",
      "lan": "e2c4",
      "before": "r2qkb1r/ppp2ppp/2n1p3/3n4/3p2b1/5N2/PPPNQPPP/R1B1KB1R w KQkq - 2 9",
      "after": "r2qkb1r/ppp2ppp/2n1p3/3n4/2Qp2b1/5N2/PPPN1PPP/R1B1KB1R b KQkq - 3 9",
      "durationMs": 4903.796875
    },
    {
      "color": "b",
      "from": "d8",
      "to": "d7",
      "piece": "q",
      "flags": "n",
      "san": "Qd7",
      "lan": "d8d7",
      "before": "r2qkb1r/ppp2ppp/2n1p3/3n4/2Qp2b1/5N2/PPPN1PPP/R1B1KB1R b KQkq - 3 9",
      "after": "r3kb1r/pppq1ppp/2n1p3/3n4/2Qp2b1/5N2/PPPN1PPP/R1B1KB1R w KQkq - 4 10",
      "durationMs": 4908.781458999962
    },
    {
      "color": "w",
      "from": "d2",
      "to": "e4",
      "piece": "n",
      "flags": "n",
      "san": "Ne4",
      "lan": "d2e4",
      "before": "r3kb1r/pppq1ppp/2n1p3/3n4/2Qp2b1/5N2/PPPN1PPP/R1B1KB1R w KQkq - 4 10",
      "after": "r3kb1r/pppq1ppp/2n1p3/3n4/2QpN1b1/5N2/PPP2PPP/R1B1KB1R b KQkq - 5 10",
      "durationMs": 4902.021707998589
    },
    {
      "color": "b",
      "from": "e8",
      "to": "c8",
      "piece": "k",
      "flags": "q",
      "san": "O-O-O",
      "lan": "e8c8",
      "before": "r3kb1r/pppq1ppp/2n1p3/3n4/2QpN1b1/5N2/PPP2PPP/R1B1KB1R b KQkq - 5 10",
      "after": "2kr1b1r/pppq1ppp/2n1p3/3n4/2QpN1b1/5N2/PPP2PPP/R1B1KB1R w KQ - 6 11",
      "durationMs": 4906.503583000973
    },
    {
      "color": "w",
      "from": "e4",
      "to": "c3",
      "piece": "n",
      "flags": "n",
      "san": "Nc3",
      "lan": "e4c3",
      "before": "2kr1b1r/pppq1ppp/2n1p3/3n4/2QpN1b1/5N2/PPP2PPP/R1B1KB1R w KQ - 6 11",
      "after": "2kr1b1r/pppq1ppp/2n1p3/3n4/2Qp2b1/2N2N2/PPP2PPP/R1B1KB1R b KQ - 7 11",
      "durationMs": 4903.443083001301
    },
    {
      "color": "b",
      "from": "g4",
      "to": "f3",
      "piece": "b",
      "captured": "n",
      "flags": "c",
      "san": "Bxf3",
      "lan": "g4f3",
      "before": "2kr1b1r/pppq1ppp/2n1p3/3n4/2Qp2b1/2N2N2/PPP2PPP/R1B1KB1R b KQ - 7 11",
      "after": "2kr1b1r/pppq1ppp/2n1p3/3n4/2Qp4/2N2b2/PPP2PPP/R1B1KB1R w KQ - 0 12",
      "durationMs": 4909.12066699937
    },
    {
      "color": "w",
      "from": "c1",
      "to": "g5",
      "piece": "b",
      "flags": "n",
      "san": "Bg5",
      "lan": "c1g5",
      "before": "2kr1b1r/pppq1ppp/2n1p3/3n4/2Qp4/2N2b2/PPP2PPP/R1B1KB1R w KQ - 0 12",
      "after": "2kr1b1r/pppq1ppp/2n1p3/3n2B1/2Qp4/2N2b2/PPP2PPP/R3KB1R b KQ - 1 12",
      "durationMs": 4902.232582999393
    },
    {
      "color": "b",
      "from": "d4",
      "to": "c3",
      "piece": "p",
      "captured": "n",
      "flags": "c",
      "san": "dxc3",
      "lan": "d4c3",
      "before": "2kr1b1r/pppq1ppp/2n1p3/3n2B1/2Qp4/2N2b2/PPP2PPP/R3KB1R b KQ - 1 12",
      "after": "2kr1b1r/pppq1ppp/2n1p3/3n2B1/2Q5/2p2b2/PPP2PPP/R3KB1R w KQ - 0 13",
      "durationMs": 4907.876832999289
    },
    {
      "color": "w",
      "from": "c4",
      "to": "b3",
      "piece": "q",
      "flags": "n",
      "san": "Qb3",
      "lan": "c4b3",
      "before": "2kr1b1r/pppq1ppp/2n1p3/3n2B1/2Q5/2p2b2/PPP2PPP/R3KB1R w KQ - 0 13",
      "after": "2kr1b1r/pppq1ppp/2n1p3/3n2B1/8/1Qp2b2/PPP2PPP/R3KB1R b KQ - 1 13",
      "durationMs": 4902.660457998514
    },
    {
      "color": "b",
      "from": "d5",
      "to": "e3",
      "piece": "n",
      "flags": "n",
      "san": "Ne3",
      "lan": "d5e3",
      "before": "2kr1b1r/pppq1ppp/2n1p3/3n2B1/8/1Qp2b2/PPP2PPP/R3KB1R b KQ - 1 13",
      "after": "2kr1b1r/pppq1ppp/2n1p3/6B1/8/1Qp1nb2/PPP2PPP/R3KB1R w KQ - 2 14",
      "durationMs": 4908.250125000253
    },
    {
      "color": "w",
      "from": "b3",
      "to": "b6",
      "piece": "q",
      "flags": "n",
      "san": "Qb6",
      "lan": "b3b6",
      "before": "2kr1b1r/pppq1ppp/2n1p3/6B1/8/1Qp1nb2/PPP2PPP/R3KB1R w KQ - 2 14",
      "after": "2kr1b1r/pppq1ppp/1Qn1p3/6B1/8/2p1nb2/PPP2PPP/R3KB1R b KQ - 3 14",
      "durationMs": 4901.796707998961
    },
    {
      "color": "b",
      "from": "e3",
      "to": "c2",
      "piece": "n",
      "captured": "p",
      "flags": "c",
      "san": "Nxc2#",
      "lan": "e3c2",
      "before": "2kr1b1r/pppq1ppp/1Qn1p3/6B1/8/2p1nb2/PPP2PPP/R3KB1R b KQ - 3 14",
      "after": "2kr1b1r/pppq1ppp/1Qn1p3/6B1/8/2p2b2/PPn2PPP/R3KB1R w KQ - 0 15",
      "durationMs": 32.614333998411894
    }
  ],
  "durationMs": 83352.33662500046
}