{
  "players": {
    "white": "tonyd33",
    "black": "girlchesser"
  },
  "type": "WIN",
  "winner": "tonyd33",
  "reason": "CHECKMATE",
  "pgn": "[Event \"?\"]\n[Site \"?\"]\n[Date \"????.??.??\"]\n[Round \"?\"]\n[White \"Silver Suite\"]\n[Black \"English, Four Knights\"]\n[Result \"*\"]\n[ECO \"A29\"]\n[PlyCount \"6\"]\n\n1. c4 e5 2. Nc3 Nf6 3. Nf3 Nc6 4. e3 Ng4 5. Bd3 Ne7 6. O-O Rb8 7. h3 e4 8. Nxe4 Nf6 9. Nxf6+ gxf6 10. b3 d5 11. Bb2 Bg7 12. Qc2 Be6 13. Nd4 Bd7 14. cxd5 Qc8 15. Be4 Kd8 16. Rac1 b5 17. Nc6+ Bxc6 18. dxc6 Qa6 19. Qd3+ Ke8 20. Qd7+ Kf8 21. Qxc7 Ra8 22. a3 b4 23. axb4 Qa2 24. Qd6 Qxb2 25. c7 Re8 26. c8=Q f5 27. Qxe8+ Kxe8 28. Rc8+ Nxc8 29. Bc6# *",
  "moves": [
    {
      "color": "w",
      "from": "e2",
      "to": "e3",
      "piece": "p",
      "flags": "n",
      "san": "e3",
      "lan": "e2e3",
      "before": "r1bqkb1r/pppp1ppp/2n2n2/4p3/2P5/2N2N2/PP1PPPPP/R1BQKB1R w KQkq - 4 4",
      "after": "r1bqkb1r/pppp1ppp/2n2n2/4p3/2P5/2N1PN2/PP1P1PPP/R1BQKB1R b KQkq - 0 4",
      "durationMs": 4945.290625
    },
    {
      "color": "b",
      "from": "f6",
      "to": "g4",
      "piece": "n",
      "flags": "n",
      "san": "Ng4",
      "lan": "f6g4",
      "before": "r1bqkb1r/pppp1ppp/2n2n2/4p3/2P5/2N1PN2/PP1P1PPP/R1BQKB1R b KQkq - 0 4",
      "after": "r1bqkb1r/pppp1ppp/2n5/4p3/2P3n1/2N1PN2/PP1P1PPP/R1BQKB1R w KQkq - 1 5",
      "durationMs": 4779.161416000001
    },
    {
      "color": "w",
      "from": "f1",
      "to": "d3",
      "piece": "b",
      "flags": "n",
      "san": "Bd3",
      "lan": "f1d3",
      "before": "r1bqkb1r/pppp1ppp/2n5/4p3/2P3n1/2N1PN2/PP1P1PPP/R1BQKB1R w KQkq - 1 5",
      "after": "r1bqkb1r/pppp1ppp/2n5/4p3/2P3n1/2NBPN2/PP1P1PPP/R1BQK2R b KQkq - 2 5",
      "durationMs": 4908.730208999999
    },
    {
      "color": "b",
      "from": "c6",
      "to": "e7",
      "piece": "n",
      "flags": "n",
      "san": "Ne7",
      "lan": "c6e7",
      "before": "r1bqkb1r/pppp1ppp/2n5/4p3/2P3n1/2NBPN2/PP1P1PPP/R1BQK2R b KQkq - 2 5",
      "after": "r1bqkb1r/ppppnppp/8/4p3/2P3n1/2NBPN2/PP1P1PPP/R1BQK2R w KQkq - 3 6",
      "durationMs": 4752.270082999999
    },
    {
      "color": "w",
      "from": "e1",
      "to": "g1",
      "piece": "k",
      "flags": "k",
      "san": "O-O",
      "lan": "e1g1",
      "before": "r1bqkb1r/ppppnppp/8/4p3/2P3n1/2NBPN2/PP1P1PPP/R1BQK2R w KQkq - 3 6",
      "after": "r1bqkb1r/ppppnppp/8/4p3/2P3n1/2NBPN2/PP1P1PPP/R1BQ1RK1 b kq - 4 6",
      "durationMs": 4906.870625
    },
    {
      "color": "b",
      "from": "a8",
      "to": "b8",
      "piece": "r",
      "flags": "n",
      "san": "Rb8",
      "lan": "a8b8",
      "before": "r1bqkb1r/ppppnppp/8/4p3/2P3n1/2NBPN2/PP1P1PPP/R1BQ1RK1 b kq - 4 6",
      "after": "1rbqkb1r/ppppnppp/8/4p3/2P3n1/2NBPN2/PP1P1PPP/R1BQ1RK1 w k - 5 7",
      "durationMs": 4751.968874999999
    },
    {
      "color": "w",
      "from": "h2",
      "to": "h3",
      "piece": "p",
      "flags": "n",
      "san": "h3",
      "lan": "h2h3",
      "before": "1rbqkb1r/ppppnppp/8/4p3/2P3n1/2NBPN2/PP1P1PPP/R1BQ1RK1 w k - 5 7",
      "after": "1rbqkb1r/ppppnppp/8/4p3/2P3n1/2NBPN1P/PP1P1PP1/R1BQ1RK1 b k - 0 7",
      "durationMs": 4909.175875000004
    },
    {
      "color": "b",
      "from": "e5",
      "to": "e4",
      "piece": "p",
      "flags": "n",
      "san": "e4",
      "lan": "e5e4",
      "before": "1rbqkb1r/ppppnppp/8/4p3/2P3n1/2NBPN1P/PP1P1PP1/R1BQ1RK1 b k - 0 7",
      "after": "1rbqkb1r/ppppnppp/8/8/2P1p1n1/2NBPN1P/PP1P1PP1/R1BQ1RK1 w k - 0 8",
      "durationMs": 4751.588917000001
    },
    {
      "color": "w",
      "from": "c3",
      "to": "e4",
      "piece": "n",
      "captured": "p",
      "flags": "c",
      "san": "Nxe4",
      "lan": "c3e4",
      "before": "1rbqkb1r/ppppnppp/8/8/2P1p1n1/2NBPN1P/PP1P1PP1/R1BQ1RK1 w k - 0 8",
      "after": "1rbqkb1r/ppppnppp/8/8/2P1N1n1/3BPN1P/PP1P1PP1/R1BQ1RK1 b k - 0 8",
      "durationMs": 4904.330500000004
    },
    {
      "color": "b",
      "from": "g4",
      "to": "f6",
      "piece": "n",
      "flags": "n",
      "san": "Nf6",
      "lan": "g4f6",
      "before": "1rbqkb1r/ppppnppp/8/8/2P1N1n1/3BPN1P/PP1P1PP1/R1BQ1RK1 b k - 0 8",
      "after": "1rbqkb1r/ppppnppp/5n2/8/2P1N3/3BPN1P/PP1P1PP1/R1BQ1RK1 w k - 1 9",
      "durationMs": 4751.698207999994
    },
    {
      "color": "w",
      "from": "e4",
      "to": "f6",
      "piece": "n",
      "captured": "n",
      "flags": "c",
      "san": "Nxf6+",
      "lan": "e4f6",
      "before": "1rbqkb1r/ppppnppp/5n2/8/2P1N3/3BPN1P/PP1P1PP1/R1BQ1RK1 w k - 1 9",
      "after": "1rbqkb1r/ppppnppp/5N2/8/2P5/3BPN1P/PP1P1PP1/R1BQ1RK1 b k - 0 9",
      "durationMs": 4908.135416999998
    },
    {
      "color": "b",
      "from": "g7",
      "to": "f6",
      "piece": "p",
      "captured": "n",
      "flags": "c",
      "san": "gxf6",
      "lan": "g7f6",
      "before": "1rbqkb1r/ppppnppp/5N2/8/2P5/3BPN1P/PP1P1PP1/R1BQ1RK1 b k - 0 9",
      "after": "1rbqkb1r/ppppnp1p/5p2/8/2P5/3BPN1P/PP1P1PP1/R1BQ1RK1 w k - 0 10",
      "durationMs": 4752.425457999998
    },
    {
      "color": "w",
      "from": "b2",
      "to": "b3",
      "piece": "p",
      "flags": "n",
      "san": "b3",
      "lan": "b2b3",
      "before": "1rbqkb1r/ppppnp1p/5p2/8/2P5/3BPN1P/PP1P1PP1/R1BQ1RK1 w k - 0 10",
      "after": "1rbqkb1r/ppppnp1p/5p2/8/2P5/1P1BPN1P/P2P1PP1/R1BQ1RK1 b k - 0 10",
      "durationMs": 4912.321541999998
    },
    {
      "color": "b",
      "from": "d7",
      "to": "d5",
      "piece": "p",
      "flags": "b",
      "san": "d5",
      "lan": "d7d5",
      "before": "1rbqkb1r/ppppnp1p/5p2/8/2P5/1P1BPN1P/P2P1PP1/R1BQ1RK1 b k - 0 10",
      "after": "1rbqkb1r/ppp1np1p/5p2/3p4/2P5/1P1BPN1P/P2P1PP1/R1BQ1RK1 w k - 0 11",
      "durationMs": 4752.299583
    },
    {
      "color": "w",
      "from": "c1",
      "to": "b2",
      "piece": "b",
      "flags": "n",
      "san": "Bb2",
      "lan": "c1b2",
      "before": "1rbqkb1r/ppp1np1p/5p2/3p4/2P5/1P1BPN1P/P2P1PP1/R1BQ1RK1 w k - 0 11",
      "after": "1rbqkb1r/ppp1np1p/5p2/3p4/2P5/1P1BPN1P/PB1P1PP1/R2Q1RK1 b k - 1 11",
      "durationMs": 4907.400041999994
    },
    {
      "color": "b",
      "from": "f8",
      "to": "g7",
      "piece": "b",
      "flags": "n",
      "san": "Bg7",
      "lan": "f8g7",
      "before": "1rbqkb1r/ppp1np1p/5p2/3p4/2P5/1P1BPN1P/PB1P1PP1/R2Q1RK1 b k - 1 11",
      "after": "1rbqk2r/ppp1npbp/5p2/3p4/2P5/1P1BPN1P/PB1P1PP1/R2Q1RK1 w k - 2 12",
      "durationMs": 4751.424708000006
    },
    {
      "color": "w",
      "from": "d1",
      "to": "c2",
      "piece": "q",
      "flags": "n",
      "san": "Qc2",
      "lan": "d1c2",
      "before": "1rbqk2r/ppp1npbp/5p2/3p4/2P5/1P1BPN1P/PB1P1PP1/R2Q1RK1 w k - 2 12",
      "after": "1rbqk2r/ppp1npbp/5p2/3p4/2P5/1P1BPN1P/PBQP1PP1/R4RK1 b k - 3 12",
      "durationMs": 4910.515750000006
    },
    {
      "color": "b",
      "from": "c8",
      "to": "e6",
      "piece": "b",
      "flags": "n",
      "san": "Be6",
      "lan": "c8e6",
      "before": "1rbqk2r/ppp1npbp/5p2/3p4/2P5/1P1BPN1P/PBQP1PP1/R4RK1 b k - 3 12",
      "after": "1r1qk2r/ppp1npbp/4bp2/3p4/2P5/1P1BPN1P/PBQP1PP1/R4RK1 w k - 4 13",
      "durationMs": 4753.588000000003
    },
    {
      "color": "w",
      "from": "f3",
      "to": "d4",
      "piece": "n",
      "flags": "n",
      "san": "Nd4",
      "lan": "f3d4",
      "before": "1r1qk2r/ppp1npbp/4bp2/3p4/2P5/1P1BPN1P/PBQP1PP1/R4RK1 w k - 4 13",
      "after": "1r1qk2r/ppp1npbp/4bp2/3p4/2PN4/1P1BP2P/PBQP1PP1/R4RK1 b k - 5 13",
      "durationMs": 4915.859540999998
    },
    {
      "color": "b",
      "from": "e6",
      "to": "d7",
      "piece": "b",
      "flags": "n",
      "san": "Bd7",
      "lan": "e6d7",
      "before": "1r1qk2r/ppp1npbp/4bp2/3p4/2PN4/1P1BP2P/PBQP1PP1/R4RK1 b k - 5 13",
      "after": "1r1qk2r/pppbnpbp/5p2/3p4/2PN4/1P1BP2P/PBQP1PP1/R4RK1 w k - 6 14",
      "durationMs": 4752.132708999998
    },
    {
      "color": "w",
      "from": "c4",
      "to": "d5",
      "piece": "p",
      "captured": "p",
      "flags": "c",
      "san": "cxd5",
      "lan": "c4d5",
      "before": "1r1qk2r/pppbnpbp/5p2/3p4/2PN4/1P1BP2P/PBQP1PP1/R4RK1 w k - 6 14",
      "after": "1r1qk2r/pppbnpbp/5p2/3P4/3N4/1P1BP2P/PBQP1PP1/R4RK1 b k - 0 14",
      "durationMs": 4908.305458000003
    },
    {
      "color": "b",
      "from": "d8",
      "to": "c8",
      "piece": "q",
      "flags": "n",
      "san": "Qc8",
      "lan": "d8c8",
      "before": "1r1qk2r/pppbnpbp/5p2/3P4/3N4/1P1BP2P/PBQP1PP1/R4RK1 b k - 0 14",
      "after": "1rq1k2r/pppbnpbp/5p2/3P4/3N4/1P1BP2P/PBQP1PP1/R4RK1 w k - 1 15",
      "durationMs": 4751.74225000001
    },
    {
      "color": "w",
      "from": "d3",
      "to": "e4",
      "piece": "b",
      "flags": "n",
      "san": "Be4",
      "lan": "d3e4",
      "before": "1rq1k2r/pppbnpbp/5p2/3P4/3N4/1P1BP2P/PBQP1PP1/R4RK1 w k - 1 15",
      "after": "1rq1k2r/pppbnpbp/5p2/3P4/3NB3/1P2P2P/PBQP1PP1/R4RK1 b k - 2 15",
      "durationMs": 4909.025041999994
    },
    {
      "color": "b",
      "from": "e8",
      "to": "d8",
      "piece": "k",
      "flags": "n",
      "san": "Kd8",
      "lan": "e8d8",
      "before": "1rq1k2r/pppbnpbp/5p2/3P4/3NB3/1P2P2P/PBQP1PP1/R4RK1 b k - 2 15",
      "after": "1rqk3r/pppbnpbp/5p2/3P4/3NB3/1P2P2P/PBQP1PP1/R4RK1 w - - 3 16",
      "durationMs": 4751.360665999993
    },
    {
      "color": "w",
      "from": "a1",
      "to": "c1",
      "piece": "r",
      "flags": "n",
      "san": "Rac1",
      "lan": "a1c1",
      "before": "1rqk3r/pppbnpbp/5p2/3P4/3NB3/1P2P2P/PBQP1PP1/R4RK1 w - - 3 16",
      "after": "1rqk3r/pppbnpbp/5p2/3P4/3NB3/1P2P2P/PBQP1PP1/2R2RK1 b - - 4 16",
      "durationMs": 4906.521832999992
    },
    {
      "color": "b",
      "from": "b7",
      "to": "b5",
      "piece": "p",
      "flags": "b",
      "san": "b5",
      "lan": "b7b5",
      "before": "1rqk3r/pppbnpbp/5p2/3P4/3NB3/1P2P2P/PBQP1PP1/2R2RK1 b - - 4 16",
      "after": "1rqk3r/p1pbnpbp/5p2/1p1P4/3NB3/1P2P2P/PBQP1PP1/2R2RK1 w - - 0 17",
      "durationMs": 4753.495874999993
    },
    {
      "color": "w",
      "from": "d4",
      "to": "c6",
      "piece": "n",
      "flags": "n",
      "san": "Nc6+",
      "lan": "d4c6",
      "before": "1rqk3r/p1pbnpbp/5p2/1p1P4/3NB3/1P2P2P/PBQP1PP1/2R2RK1 w - - 0 17",
      "after": "1rqk3r/p1pbnpbp/2N2p2/1p1P4/4B3/1P2P2P/PBQP1PP1/2R2RK1 b - - 1 17",
      "durationMs": 4914.409
    },
    {
      "color": "b",
      "from": "d7",
      "to": "c6",
      "piece": "b",
      "captured": "n",
      "flags": "c",
      "san": "Bxc6",
      "lan": "d7c6",
      "before": "1rqk3r/p1pbnpbp/2N2p2/1p1P4/4B3/1P2P2P/PBQP1PP1/2R2RK1 b - - 1 17",
      "after": "1rqk3r/p1p1npbp/2b2p2/1p1P4/4B3/1P2P2P/PBQP1PP1/2R2RK1 w - - 0 18",
      "durationMs": 4752.106208000012
    },
    {
      "color": "w",
      "from": "d5",
      "to": "c6",
      "piece": "p",
      "captured": "b",
      "flags": "c",
      "san": "dxc6",
      "lan": "d5c6",
      "before": "1rqk3r/p1p1npbp/2b2p2/1p1P4/4B3/1P2P2P/PBQP1PP1/2R2RK1 w - - 0 18",
      "after": "1rqk3r/p1p1npbp/2P2p2/1p6/4B3/1P2P2P/PBQP1PP1/2R2RK1 b - - 0 18",
      "durationMs": 4909.262874999986
    },
    {
      "color": "b",
      "from": "c8",
      "to": "a6",
      "piece": "q",
      "flags": "n",
      "san": "Qa6",
      "lan": "c8a6",
      "before": "1rqk3r/p1p1npbp/2P2p2/1p6/4B3/1P2P2P/PBQP1PP1/2R2RK1 b - - 0 18",
      "after": "1r1k3r/p1p1npbp/q1P2p2/1p6/4B3/1P2P2P/PBQP1PP1/2R2RK1 w - - 1 19",
      "durationMs": 4751.386375000002
    },
    {
      "color": "w",
      "from": "c2",
      "to": "d3",
      "piece": "q",
      "flags": "n",
      "san": "Qd3+",
      "lan": "c2d3",
      "before": "1r1k3r/p1p1npbp/q1P2p2/1p6/4B3/1P2P2P/PBQP1PP1/2R2RK1 w - - 1 19",
      "after": "1r1k3r/p1p1npbp/q1P2p2/1p6/4B3/1P1QP2P/PB1P1PP1/2R2RK1 b - - 2 19",
      "durationMs": 4907.207708000002
    },
    {
      "color": "b",
      "from": "d8",
      "to": "e8",
      "piece": "k",
      "flags": "n",
      "san": "Ke8",
      "lan": "d8e8",
      "before": "1r1k3r/p1p1npbp/q1P2p2/1p6/4B3/1P1QP2P/PB1P1PP1/2R2RK1 b - - 2 19",
      "after": "1r2k2r/p1p1npbp/q1P2p2/1p6/4B3/1P1QP2P/PB1P1PP1/2R2RK1 w - - 3 20",
      "durationMs": 4752.0555830000085
    },
    {
      "color": "w",
      "from": "d3",
      "to": "d7",
      "piece": "q",
      "flags": "n",
      "san": "Qd7+",
      "lan": "d3d7",
      "before": "1r2k2r/p1p1npbp/q1P2p2/1p6/4B3/1P1QP2P/PB1P1PP1/2R2RK1 w - - 3 20",
      "after": "1r2k2r/p1pQnpbp/q1P2p2/1p6/4B3/1P2P2P/PB1P1PP1/2R2RK1 b - - 4 20",
      "durationMs": 4909.654041000002
    },
    {
      "color": "b",
      "from": "e8",
      "to": "f8",
      "piece": "k",
      "flags": "n",
      "san": "Kf8",
      "lan": "e8f8",
      "before": "1r2k2r/p1pQnpbp/q1P2p2/1p6/4B3/1P2P2P/PB1P1PP1/2R2RK1 b - - 4 20",
      "after": "1r3k1r/p1pQnpbp/q1P2p2/1p6/4B3/1P2P2P/PB1P1PP1/2R2RK1 w - - 5 21",
      "durationMs": 4751.543291999988
    },
    {
      "color": "w",
      "from": "d7",
      "to": "c7",
      "piece": "q",
      "captured": "p",
      "flags": "c",
      "san": "Qxc7",
      "lan": "d7c7",
      "before": "1r3k1r/p1pQnpbp/q1P2p2/1p6/4B3/1P2P2P/PB1P1PP1/2R2RK1 w - - 5 21",
      "after": "1r3k1r/p1Q1npbp/q1P2p2/1p6/4B3/1P2P2P/PB1P1PP1/2R2RK1 b - - 0 21",
      "durationMs": 4907.528625000006
    },
    {
      "color": "b",
      "from": "b8",
      "to": "a8",
      "piece": "r",
      "flags": "n",
      "san": "Ra8",
      "lan": "b8a8",
      "before": "1r3k1r/p1Q1npbp/q1P2p2/1p6/4B3/1P2P2P/PB1P1PP1/2R2RK1 b - - 0 21",
      "after": "r4k1r/p1Q1npbp/q1P2p2/1p6/4B3/1P2P2P/PB1P1PP1/2R2RK1 w - - 1 22",
      "durationMs": 4753.703749999986
    },
    {
      "color": "w",
      "from": "a2",
      "to": "a3",
      "piece": "p",
      "flags": "n",
      "san": "a3",
      "lan": "a2a3",
      "before": "r4k1r/p1Q1npbp/q1P2p2/1p6/4B3/1P2P2P/PB1P1PP1/2R2RK1 w - - 1 22",
      "after": "r4k1r/p1Q1npbp/q1P2p2/1p6/4B3/PP2P2P/1B1P1PP1/2R2RK1 b - - 0 22",
      "durationMs": 4914.046457999997
    },
    {
      "color": "b",
      "from": "b5",
      "to": "b4",
      "piece": "p",
      "flags": "n",
      "san": "b4",
      "lan": "b5b4",
      "before": "r4k1r/p1Q1npbp/q1P2p2/1p6/4B3/PP2P2P/1B1P1PP1/2R2RK1 b - - 0 22",
      "after": "r4k1r/p1Q1npbp/q1P2p2/8/1p2B3/PP2P2P/1B1P1PP1/2R2RK1 w - - 0 23",
      "durationMs": 4752.227416999987
    },
    {
      "color": "w",
      "from": "a3",
      "to": "b4",
      "piece": "p",
      "captured": "p",
      "flags": "c",
      "san": "axb4",
      "lan": "a3b4",
      "before": "r4k1r/p1Q1npbp/q1P2p2/8/1p2B3/PP2P2P/1B1P1PP1/2R2RK1 w - - 0 23",
      "after": "r4k1r/p1Q1npbp/q1P2p2/8/1P2B3/1P2P2P/1B1P1PP1/2R2RK1 b - - 0 23",
      "durationMs": 4907.167375000019
    },
    {
      "color": "b",
      "from": "a6",
      "to": "a2",
      "piece": "q",
      "flags": "n",
      "san": "Qa2",
      "lan": "a6a2",
      "before": "r4k1r/p1Q1npbp/q1P2p2/8/1P2B3/1P2P2P/1B1P1PP1/2R2RK1 b - - 0 23",
      "after": "r4k1r/p1Q1npbp/2P2p2/8/1P2B3/1P2P2P/qB1P1PP1/2R2RK1 w - - 1 24",
      "durationMs": 4751.955707999994
    },
    {
      "color": "w",
      "from": "c7",
      "to": "d6",
      "piece": "q",
      "flags": "n",
      "san": "Qd6",
      "lan": "c7d6",
      "before": "r4k1r/p1Q1npbp/2P2p2/8/1P2B3/1P2P2P/qB1P1PP1/2R2RK1 w - - 1 24",
      "after": "r4k1r/p3npbp/2PQ1p2/8/1P2B3/1P2P2P/qB1P1PP1/2R2RK1 b - - 2 24",
      "durationMs": 4907.379625000001
    },
    {
      "color": "b",
      "from": "a2",
      "to": "b2",
      "piece": "q",
      "captured": "b",
      "flags": "c",
      "san": "Qxb2",
      "lan": "a2b2",
      "before": "r4k1r/p3npbp/2PQ1p2/8/1P2B3/1P2P2P/qB1P1PP1/2R2RK1 b - - 2 24",
      "after": "r4k1r/p3npbp/2PQ1p2/8/1P2B3/1P2P2P/1q1P1PP1/2R2RK1 w - - 0 25",
      "durationMs": 4752.091167000006
    },
    {
      "color": "w",
      "from": "c6",
      "to": "c7",
      "piece": "p",
      "flags": "n",
      "san": "c7",
      "lan": "c6c7",
      "before": "r4k1r/p3npbp/2PQ1p2/8/1P2B3/1P2P2P/1q1P1PP1/2R2RK1 w - - 0 25",
      "after": "r4k1r/p1P1npbp/3Q1p2/8/1P2B3/1P2P2P/1q1P1PP1/2R2RK1 b - - 0 25",
      "durationMs": 4906.576624999987
    },
    {
      "color": "b",
      "from": "a8",
      "to": "e8",
      "piece": "r",
      "flags": "n",
      "san": "Re8",
      "lan": "a8e8",
      "before": "r4k1r/p1P1npbp/3Q1p2/8/1P2B3/1P2P2P/1q1P1PP1/2R2RK1 b - - 0 25",
      "after": "4rk1r/p1P1npbp/3Q1p2/8/1P2B3/1P2P2P/1q1P1PP1/2R2RK1 w - - 1 26",
      "durationMs": 4753.261709000013
    },
    {
      "color": "w",
      "from": "c7",
      "to": "c8",
      "piece": "p",
      "promotion": "q",
      "flags": "np",
      "san": "c8=Q",
      "lan": "c7c8q",
      "before": "4rk1r/p1P1npbp/3Q1p2/8/1P2B3/1P2P2P/1q1P1PP1/2R2RK1 w - - 1 26",
      "after": "2Q1rk1r/p3npbp/3Q1p2/8/1P2B3/1P2P2P/1q1P1PP1/2R2RK1 b - - 0 26",
      "durationMs": 4907.812291999988
    },
    {
      "color": "b",
      "from": "f6",
      "to": "f5",
      "piece": "p",
      "flags": "n",
      "san": "f5",
      "lan": "f6f5",
      "before": "2Q1rk1r/p3npbp/3Q1p2/8/1P2B3/1P2P2P/1q1P1PP1/2R2RK1 b - - 0 26",
      "after": "2Q1rk1r/p3npbp/3Q4/5p2/1P2B3/1P2P2P/1q1P1PP1/2R2RK1 w - - 0 27",
      "durationMs": 4752.429499999998
    },
    {
      "color": "w",
      "from": "c8",
      "to": "e8",
      "piece": "q",
      "captured": "r",
      "flags": "c",
      "san": "Qxe8+",
      "lan": "c8e8",
      "before": "2Q1rk1r/p3npbp/3Q4/5p2/1P2B3/1P2P2P/1q1P1PP1/2R2RK1 w - - 0 27",
      "after": "4Qk1r/p3npbp/3Q4/5p2/1P2B3/1P2P2P/1q1P1PP1/2R2RK1 b - - 0 27",
      "durationMs": 13.756916999991518
    },
    {
      "color": "b",
      "from": "f8",
      "to": "e8",
      "piece": "k",
      "captured": "q",
      "flags": "c",
      "san": "Kxe8",
      "lan": "f8e8",
      "before": "4Qk1r/p3npbp/3Q4/5p2/1P2B3/1P2P2P/1q1P1PP1/2R2RK1 b - - 0 27",
      "after": "4k2r/p3npbp/3Q4/5p2/1P2B3/1P2P2P/1q1P1PP1/2R2RK1 w - - 0 28",
      "durationMs": 4752.348208999989
    },
    {
      "color": "w",
      "from": "c1",
      "to": "c8",
      "piece": "r",
      "flags": "n",
      "san": "Rc8+",
      "lan": "c1c8",
      "before": "4k2r/p3npbp/3Q4/5p2/1P2B3/1P2P2P/1q1P1PP1/2R2RK1 w - - 0 28",
      "after": "2R1k2r/p3npbp/3Q4/5p2/1P2B3/1P2P2P/1q1P1PP1/5RK1 b - - 1 28",
      "durationMs": 11.062917000002926
    },
    {
      "color": "b",
      "from": "e7",
      "to": "c8",
      "piece": "n",
      "captured": "r",
      "flags": "c",
      "san": "Nxc8",
      "lan": "e7c8",
      "before": "2R1k2r/p3npbp/3Q4/5p2/1P2B3/1P2P2P/1q1P1PP1/5RK1 b - - 1 28",
      "after": "2n1k2r/p4pbp/3Q4/5p2/1P2B3/1P2P2P/1q1P1PP1/5RK1 w - - 0 29",
      "durationMs": 4751.6231670000125
    },
    {
      "color": "w",
      "from": "e4",
      "to": "c6",
      "piece": "b",
      "flags": "n",
      "san": "Bc6#",
      "lan": "e4c6",
      "before": "2n1k2r/p4pbp/3Q4/5p2/1P2B3/1P2P2P/1q1P1PP1/5RK1 w - - 0 29",
      "after": "2n1k2r/p4pbp/2BQ4/5p2/1P6/1P2P2P/1q1P1PP1/5RK1 b - - 1 29",
      "durationMs": 29.14308300000266
    }
  ],
  "durationMs": 231881.68675
}